LICENSE
README.md
setup.py
autopromptgen/__init__.py
autopromptgen/engine.py
autopromptgen/utils.py
autopromptgen.egg-info/PKG-INFO
autopromptgen.egg-info/SOURCES.txt
autopromptgen.egg-info/dependency_links.txt
autopromptgen.egg-info/top_level.txt