Metadata-Version: 2.4
Name: autopromptgen
Version: 0.1.0
Summary: Auto Prompt Generator without API keys for open-source AI
Author: Chittepu Sree Keerthi Reddy
Author-email: keerthichittepu965@gmail.com
Classifier: Programming Language :: Python :: 3
Classifier: License :: OSI Approved :: MIT License
License-File: LICENSE
Dynamic: author
Dynamic: author-email
Dynamic: classifier
Dynamic: license-file
Dynamic: summary
